strainedsmiles2xyz/__init__.py
strainedsmiles2xyz/__main__.py
strainedsmiles2xyz/cli.py
strainedsmiles2xyz-0.2.3.dist-info/licenses/LICENSE
strainedsmiles2xyz-0.2.3.dist-info/METADATA
strainedsmiles2xyz-0.2.3.dist-info/WHEEL
strainedsmiles2xyz-0.2.3.dist-info/entry_points.txt
strainedsmiles2xyz-0.2.3.dist-info/top_level.txt
strainedsmiles2xyz-0.2.3.dist-info/RECORD
