Metadata-Version: 2.4
Name: strainedsmiles2xyz
Version: 0.2.3
Summary: Convert strained SMILES to XYZ coordinates with stereocontrol
Author-email: Dennis Svatunek <dennis.svatunek@tuwien.ac.at>
License:                     GNU GENERAL PUBLIC LICENSE
Project-URL: Homepage, https://github.com/Svatunek-Lab/strainedSMILES2xyz
Requires-Python: >=3.8
License-File: LICENSE
Dynamic: license-file
